MANIFEST.in
README
requirements.txt
setup.py
ajenti.plugin.softraid.egg-info/PKG-INFO
ajenti.plugin.softraid.egg-info/SOURCES.txt
ajenti.plugin.softraid.egg-info/dependency_links.txt
ajenti.plugin.softraid.egg-info/top_level.txt
ajenti_plugin_softraid/.gitignore
ajenti_plugin_softraid/README.md
ajenti_plugin_softraid/__init__.py
ajenti_plugin_softraid/main.py
ajenti_plugin_softraid/plugin.yml
ajenti_plugin_softraid/requirements.txt
ajenti_plugin_softraid/softraid.py
ajenti_plugin_softraid/views.py
ajenti_plugin_softraid/locale/af/LC_MESSAGES/app.js
ajenti_plugin_softraid/locale/af/LC_MESSAGES/app.po
ajenti_plugin_softraid/locale/ar/LC_MESSAGES/app.js
ajenti_plugin_softraid/locale/ar/LC_MESSAGES/app.po
ajenti_plugin_softraid/locale/be/LC_MESSAGES/app.js
ajenti_plugin_softraid/locale/be/LC_MESSAGES/app.po
ajenti_plugin_softraid/locale/bg/LC_MESSAGES/app.js
ajenti_plugin_softraid/locale/bg/LC_MESSAGES/app.po
ajenti_plugin_softraid/locale/bn/LC_MESSAGES/app.js
ajenti_plugin_softraid/locale/bn/LC_MESSAGES/app.po
ajenti_plugin_softraid/locale/bs/LC_MESSAGES/app.js
ajenti_plugin_softraid/locale/bs/LC_MESSAGES/app.po
ajenti_plugin_softraid/locale/ca/LC_MESSAGES/app.js
ajenti_plugin_softraid/locale/ca/LC_MESSAGES/app.po
ajenti_plugin_softraid/locale/cs/LC_MESSAGES/app.js
ajenti_plugin_softraid/locale/cs/LC_MESSAGES/app.po
ajenti_plugin_softraid/locale/da/LC_MESSAGES/app.js
ajenti_plugin_softraid/locale/da/LC_MESSAGES/app.po
ajenti_plugin_softraid/locale/de/LC_MESSAGES/app.js
ajenti_plugin_softraid/locale/de/LC_MESSAGES/app.po
ajenti_plugin_softraid/locale/el/LC_MESSAGES/app.js
ajenti_plugin_softraid/locale/el/LC_MESSAGES/app.po
ajenti_plugin_softraid/locale/en/LC_MESSAGES/app.po
ajenti_plugin_softraid/locale/eo/LC_MESSAGES/app.js
ajenti_plugin_softraid/locale/eo/LC_MESSAGES/app.po
ajenti_plugin_softraid/locale/es-ES/LC_MESSAGES/app.js
ajenti_plugin_softraid/locale/es-ES/LC_MESSAGES/app.po
ajenti_plugin_softraid/locale/et/LC_MESSAGES/app.js
ajenti_plugin_softraid/locale/et/LC_MESSAGES/app.po
ajenti_plugin_softraid/locale/fa/LC_MESSAGES/app.js
ajenti_plugin_softraid/locale/fa/LC_MESSAGES/app.po
ajenti_plugin_softraid/locale/fi/LC_MESSAGES/app.js
