Metadata-Version: 1.2
Name: ajenti.plugin.softraid
Version: 0.4
Summary: Softraid
Home-page: https://ajenti.org
Author: Arnaud Kientz
Author-email: arnaud@linuxmuster.net
License: UNKNOWN
Platform: UNKNOWN
Requires-Python: >=3
